{"credit":"Made by Overseer","textures":{"0":"soussanchouztext/soussanchouz","particle":"soussanchouztext/soussanchouz"},"elements":[{"from":[3,0,8.5],"to":[5.5,1.5,12],"rotation":{"angle":0,"axis":"y","origin":[11,8,19]},"faces":{"north":{"uv":[0,12.35979,16,16],"texture":"#0"},"east":{"uv":[0,12.41623,15.97178,16],"texture":"#0"},"south":{"uv":[0.16931,12.35979,15.97178,16],"texture":"#0"},"west":{"uv":[0,12.30335,15.97178,16],"texture":"#0"},"up":{"uv":[0,0,2.5,3.5],"texture":"#missing"},"down":{"uv":[2.39859,13.82716,6.4903,14.61728],"texture":"#0"}}},{"from":[2.8,1.5,8.3],"to":[5.7,1.6,12.2],"rotation":{"angle":0,"axis":"y","origin":[11,9.5,19]},"faces":{"north":{"uv":[2.53968,12.64198,5.44621,13.37566],"texture":"#0"},"east":{"uv":[2.53968,12.47266,6.32099,13.26279],"texture":"#0"},"south":{"uv":[0,12.24691,2.73721,13.17813],"texture":"#0"},"west":{"uv":[2.05996,12.89594,5.95414,13.26279],"texture":"#0"},"up":{"uv":[4.17637,2.93474,11.00529,11.73898],"texture":"#0"},"down":{"uv":[3.18871,14.22222,4.34568,14.47619],"texture":"#0"}}},{"from":[9.7,0,5.1],"to":[12.2,1.5,8.6],"rotation":{"angle":22.5,"axis":"y","origin":[17.7,8,15.6]},"faces":{"north":{"uv":[0,12.35979,16,16],"texture":"#0"},"east":{"uv":[0,12.41623,15.97178,16],"texture":"#0"},"south":{"uv":[0.16931,12.35979,15.97178,16],"texture":"#0"},"west":{"uv":[0,12.30335,15.97178,16],"texture":"#0"},"up":{"uv":[0,0,2.5,3.5],"texture":"#0"},"down":{"uv":[2.39859,13.82716,6.4903,14.61728],"texture":"#0"}}},{"from":[9.5,1.5,4.9],"to":[12.4,1.6,8.8],"rotation":{"angle":22.5,"axis":"y","origin":[17.7,9.5,15.6]},"faces":{"north":{"uv":[2.53968,12.64198,5.44621,13.37566],"texture":"#0"},"east":{"uv":[2.53968,12.47266,6.32099,13.26279],"texture":"#0"},"south":{"uv":[0,12.24691,2.73721,13.17813],"texture":"#0"},"west":{"uv":[2.05996,12.89594,5.95414,13.26279],"texture":"#0"},"up":{"uv":[4.17637,2.93474,11.00529,11.73898],"texture":"#0"},"down":{"uv":[3.18871,14.22222,4.34568,14.47619],"texture":"#0"}}},{"from":[0.9,0,1.6],"to":[4.4,1.5,4.1],"rotation":{"angle":22.5,"axis":"y","origin":[11.4,8,-3.9]},"faces":{"north":{"uv":[0,12.41623,15.97178,16],"texture":"#0"},"east":{"uv":[0.16931,12.35979,15.97178,16],"texture":"#0"},"south":{"uv":[0,12.30335,15.97178,16],"texture":"#0"},"west":{"uv":[0,12.35979,16,16],"texture":"#0"},"up":{"uv":[0,0,2.5,3.5],"rotation":270,"texture":"#0"},"down":{"uv":[2.39859,13.82716,6.4903,14.61728],"rotation":90,"texture":"#0"}}},{"from":[0.7,1.5,1.4],"to":[4.6,1.6,4.3],"rotation":{"angle":22.5,"axis":"y","origin":[11.4,9.5,-3.9]},"faces":{"north":{"uv":[2.53968,12.47266,6.32099,13.26279],"texture":"#0"},"east":{"uv":[0,12.24691,2.73721,13.17813],"texture":"#0"},"south":{"uv":[2.05996,12.89594,5.95414,13.26279],"texture":"#0"},"west":{"uv":[2.53968,12.64198,5.44621,13.37566],"texture":"#0"},"up":{"uv":[4.17637,2.93474,11.00529,11.73898],"rotation":270,"texture":"#0"},"down":{"uv":[3.18871,14.22222,4.34568,14.47619],"rotation":90,"texture":"#0"}}}],"display":{"thirdperson_righthand":{"translation":[1,4.75,2],"scale":[0.57227,0.57227,0.57227]},"thirdperson_lefthand":{"translation":[-0.75,4.25,1.75],"scale":[0.51563,0.51563,0.51563]},"firstperson_righthand":{"translation":[3.5,9,-0.25]},"firstperson_lefthand":{"translation":[0,9.25,0]},"ground":{"translation":[0,4.5,0]},"gui":{"rotation":[26,15.25,0],"translation":[2,10,0],"scale":[1.53906,1.53906,1.53906]},"head":{"translation":[0,14.5,0]},"fixed":{"rotation":[-90.5,0,0],"translation":[0,0,-13.5],"scale":[1.5918,1.5918,1.5918]}},"groups":[{"name":"souce","origin":[11,9.5,19],"children":[0,1,{"name":"souce","origin":[11,9.5,19],"children":[2,3,{"name":"souce","origin":[11,9.5,19],"children":[4,5]}]}]}]}