{"credit":"Made with Blockbench","display":{"firstperson_lefthand":{"rotation":[83,0,-53],"translation":[4.75,0,0]},"firstperson_righthand":{"rotation":[67,0,-51],"translation":[4.5,0,0]},"fixed":{"rotation":[0,-90,0],"scale":[1.52,1.52,1.52],"translation":[0,0.25,1]},"ground":{"rotation":[0,0,-90],"translation":[2.5,-3.5,0.75]},"gui":{"rotation":[0,90,0],"scale":[1.18,1.18,1.18],"translation":[0.75,3,0]},"head":{"rotation":[0,-91,0],"translation":[0,6,-6.5]},"thirdperson_lefthand":{"rotation":[0,90,0],"scale":[0.65,0.65,0.65],"translation":[0,1.75,1.25]},"thirdperson_righthand":{"rotation":[0,-90,0],"scale":[0.65,0.65,0.65],"translation":[-0.25,2,0.75]}},"elements":[{"faces":{"down":{"texture":"#0","uv":[0,15.5,15.75,16]},"east":{"texture":"#0","uv":[0,6.5,15.75,12.75]},"north":{"texture":"#0","uv":[0,15.5,15.75,16]},"south":{"texture":"#0","uv":[0,15.5,15.75,16]},"up":{"texture":"#0","uv":[0,15.5,15.75,16]},"west":{"texture":"#0","uv":[0.25,0,16,6.25]}},"from":[8,3,1.5],"rotation":{"angle":0,"axis":"y","origin":[16,11,11.5]},"to":[8,8.25,13.5]}],"textures":{"0":"spore/ticket","particle":"spore/ticket"}}