{"credit":"Made with Blockbench","display":{"firstperson_lefthand":{"rotation":[0,-90,0],"translation":[0,2.5,1.25]},"firstperson_righthand":{"rotation":[0,-90,0],"translation":[0,2.5,1.25]},"fixed":{"scale":[1.72,1.72,1.72],"translation":[0,1.5,-0.5]},"ground":{"rotation":[90,0,0],"translation":[0,-1,1.25]},"gui":{"rotation":[0,32,45],"scale":[0.98,0.98,0.98],"translation":[0.75,-0.25,0]},"head":{"rotation":[0,0,115],"translation":[5.5,9.25,0.5]},"thirdperson_lefthand":{"rotation":[0,-90,0],"translation":[0,2.5,1.25]},"thirdperson_righthand":{"rotation":[0,-90,0],"translation":[0,2.5,1.5]}},"elements":[{"faces":{"down":{"texture":"#0","uv":[6,0,7,15]},"east":{"texture":"#0","uv":[6,0,7,15]},"north":{"texture":"#0","uv":[6,0,7,15]},"south":{"texture":"#0","uv":[6,0,7,15]},"up":{"texture":"#0","uv":[6,0,7,1]},"west":{"texture":"#0","uv":[6,0,7,15]}},"from":[7.5,0,7.5],"rotation":{"angle":0,"axis":"y","origin":[15.5,8,15.5]},"to":[8.5,15,8.5]},{"faces":{"down":{"texture":"#0","uv":[7,3,8,4]},"east":{"texture":"#0","uv":[7,3,8,4]},"north":{"texture":"#0","uv":[7,3,8,4]},"south":{"texture":"#0","uv":[7,3,8,4]},"up":{"texture":"#0","uv":[7,3,8,4]},"west":{"texture":"#0","uv":[7,3,8,4]}},"from":[7.65,15,7.65],"rotation":{"angle":0,"axis":"y","origin":[15.5,8,15.5]},"to":[8.35,15.15,8.35]},{"faces":{"down":{"texture":"#3","uv":[4,8,12,9]},"east":{"texture":"#3","uv":[10,8,11,10]},"north":{"rotation":180,"texture":"#3","uv":[2,8,10,10]},"south":{"rotation":180,"texture":"#3","uv":[4,8,12,10]},"up":{"texture":"#3","uv":[3,9,11,10]},"west":{"texture":"#3","uv":[7,8,8,10]}},"from":[5.3,12.8,7.2],"rotation":{"angle":0,"axis":"y","origin":[15.5,21.5,15.35]},"to":[10.5,14.5,8.75]},{"faces":{"down":{"texture":"#3","uv":[4,8,12,9]},"east":{"texture":"#3","uv":[10,8,11,10]},"north":{"rotation":180,"texture":"#3","uv":[2,8,10,10]},"south":{"rotation":180,"texture":"#3","uv":[4,8,12,10]},"up":{"texture":"#3","uv":[3,9,11,10]},"west":{"texture":"#3","uv":[7,8,8,10]}},"from":[12.45606,8.43376,7.4],"rotation":{"angle":-22.5,"axis":"z","origin":[22.95606,16.93376,15.35]},"to":[15.45606,9.73376,8.55]},{"faces":{"down":{"texture":"#3","uv":[4,8,12,9]},"east":{"texture":"#3","uv":[10,8,11,10]},"north":{"rotation":180,"texture":"#3","uv":[2,8,10,10]},"south":{"rotation":180,"texture":"#3","uv":[4,8,12,10]},"up":{"texture":"#3","uv":[3,9,11,10]},"west":{"texture":"#3","uv":[7,8,8,10]}},"from":[-1.02622,15.32206,7.4],"rotation":{"angle":22.5,"axis":"z","origin":[9.47378,23.82206,15.35]},"to":[1.97378,16.62206,8.55]},{"faces":{"down":{"texture":"#3","uv":[4,8,12,9]},"east":{"rotation":180,"texture":"#3","uv":[10,8,11,10]},"north":{"rotation":180,"texture":"#3","uv":[2,8,10,10]},"south":{"rotation":180,"texture":"#3","uv":[4,8,12,10]},"up":{"texture":"#3","uv":[3,9,11,10]},"west":{"texture":"#3","uv":[7,8,8,10]}},"from":[15.28743,2.5185,7.6],"rotation":{"angle":-45,"axis":"z","origin":[25.78743,10.8185,15.35]},"to":[17.28743,3.4185,8.35]},{"faces":{"down":{"rotation":90,"texture":"#3","uv":[7,8,8,10]},"east":{"rotation":270,"texture":"#3","uv":[4,8,12,9]},"north":{"rotation":270,"texture":"#3","uv":[2,8,10,10]},"south":{"rotation":90,"texture":"#3","uv":[4,8,12,10]},"up":{"rotation":270,"texture":"#3","uv":[10,8,11,10]},"west":{"rotation":270,"texture":"#3","uv":[3,9,11,10]}},"from":[10.70618,13.69495,7.6],"rotation":{"angle":-45,"axis":"z","origin":[3.30618,24.19495,15.35]},"to":[11.60618,15.69495,8.35]}],"groups":[{"children":[0,1],"name":"Палка","origin":[8,8,8]},{"children":[2,3,4,5,6],"name":"Верхняя часть","origin":[15.5,8,15.5]},{"children":[],"name":"Нижняя хрень","origin":[8,8,8]}],"textures":{"0":"block/oak_log","3":"block/iron_block","particle":"block/oak_log"}}