{"credit":"Made with Blockbench","textures":{"1":"mauzer/mauzer2"},"elements":[{"from":[8,0,15],"to":[9,6,17],"rotation":{"angle":-22.5,"axis":"x","origin":[9,2.5,16]},"faces":{"north":{"uv":[2.08,0,3.04,6.08],"texture":"#1"},"east":{"uv":[0,0.16,2.08,6.08],"texture":"#1"},"south":{"uv":[3.04,0,4,6.08],"texture":"#1"},"west":{"uv":[0,0,2,6],"texture":"#1"},"up":{"uv":[0.8,1.92,1.76,3.84],"texture":"#1"},"down":{"uv":[2.24,1.44,3.2,3.36],"texture":"#1"}}},{"from":[7,5,14],"to":[10,7,16],"rotation":{"angle":0,"axis":"y","origin":[16,13,22]},"faces":{"north":{"uv":[12,7.52,15.04,9.44],"texture":"#missing"},"east":{"uv":[7.68,5.6,11.36,7.52],"texture":"#1"},"south":{"uv":[11.52,5.12,14.56,7.2],"texture":"#1"},"west":{"uv":[7.84,5.6,11.36,7.52],"texture":"#1"},"up":{"uv":[11.68,4.16,14.72,6.08],"texture":"#1"},"down":{"uv":[10.56,3.36,11.36,5.76],"texture":"#1"}}},{"from":[8,7,14],"to":[9,8,15],"rotation":{"angle":0,"axis":"y","origin":[16,15,22]},"faces":{"north":{"uv":[12.16,8.32,13.12,9.28],"texture":"#missing"},"east":{"uv":[10.08,5.12,11.04,6.08],"texture":"#1"},"south":{"uv":[11.84,4.48,12.8,5.44],"texture":"#1"},"west":{"uv":[13.28,3.68,14.24,4.64],"texture":"#1"},"up":{"uv":[13.12,5.6,14.08,6.56],"texture":"#1"},"down":{"uv":[13.76,6.24,14.72,7.2],"texture":"#missing"}}},{"from":[8,6,-2],"to":[9,7,9],"rotation":{"angle":0,"axis":"y","origin":[16,14,16]},"faces":{"north":{"uv":[6.72,10.24,7.2,10.72],"texture":"#1"},"east":{"uv":[12,3.84,12.64,6.24],"texture":"#1"},"south":{"uv":[13.44,4.32,14.4,5.28],"texture":"#missing"},"west":{"uv":[11.84,5.12,12.64,7.04],"texture":"#1"},"up":{"uv":[11.84,0,12.48,7.36],"texture":"#1"},"down":{"uv":[12,0.96,12.96,7.2],"texture":"#1"}}},{"from":[8,7,8],"to":[9,8,10],"rotation":{"angle":0,"axis":"y","origin":[16,15,17]},"faces":{"north":{"uv":[13.28,5.12,14.24,6.08],"texture":"#1"},"east":{"uv":[13.6,5.92,16,7.36],"texture":"#1"},"south":{"uv":[13.12,4.32,14.08,5.28],"texture":"#missing"},"west":{"uv":[13.44,4.48,15.68,6.08],"texture":"#1"},"up":{"uv":[13.28,5.28,14.24,7.2],"texture":"#1"},"down":{"uv":[13.28,9.92,14.24,11.84],"texture":"#missing"}}},{"from":[7,5,9],"to":[10,7,14],"rotation":{"angle":0,"axis":"y","origin":[16,15,21]},"faces":{"north":{"uv":[11.68,3.68,14.72,6.72],"texture":"#1"},"east":{"uv":[11.36,3.68,15.84,6.72],"texture":"#1"},"south":{"uv":[12.64,4.32,15.68,7.36],"texture":"#missing"},"west":{"uv":[11.36,4.32,16,7.36],"texture":"#1"},"up":{"uv":[13.12,1.76,16,6.72],"texture":"#1"},"down":{"uv":[10.56,2.88,10.88,7.04],"texture":"#1"}}},{"from":[7,7,10],"to":[10,8,14],"rotation":{"angle":0,"axis":"y","origin":[16,17,21]},"faces":{"north":{"uv":[9.28,3.2,11.2,6.24],"texture":"#1"},"east":{"uv":[11.52,4.16,14.72,5.76],"texture":"#1"},"south":{"uv":[7.84,2.88,10.88,5.92],"texture":"#1"},"west":{"uv":[9.28,1.92,12.48,4.96],"texture":"#1"},"up":{"uv":[11.52,0.64,14.4,5.6],"texture":"#1"},"down":{"uv":[11.04,4,12.8,8.96],"texture":"#missing"}}},{"from":[8,3,8.8],"to":[9,6,12],"rotation":{"angle":0,"axis":"y","origin":[16,12,21]},"faces":{"north":{"uv":[10.24,12.8,12,16],"texture":"#1"},"east":{"uv":[10.4,12.8,11.52,15.36],"texture":"#1"},"south":{"uv":[10.4,12.8,11.52,15.36],"texture":"#1"},"west":{"uv":[10.4,12.8,11.52,15.36],"texture":"#1"},"up":{"uv":[10.4,12.8,11.52,15.36],"texture":"#1"},"down":{"uv":[10.4,12.8,11.52,15.36],"texture":"#1"}}},{"from":[8,3,12],"to":[9,5,14],"rotation":{"angle":0,"axis":"y","origin":[16,12,20]},"faces":{"north":{"uv":[12.96,5.28,15.36,7.84],"texture":"#missing"},"east":{"uv":[10.24,10.24,12.8,12.8],"texture":"#1"},"south":{"uv":[15.04,1.28,16,3.2],"texture":"#1"},"west":{"uv":[10.24,10.24,12.8,12.8],"rotation":90,"texture":"#1"},"up":{"uv":[13.12,3.04,14.56,5.6],"texture":"#1"},"down":{"uv":[15.04,3.36,15.68,5.44],"texture":"#1"}}},{"from":[8,7,-1],"to":[9,8,0],"rotation":{"angle":0,"axis":"y","origin":[16,15,7]},"faces":{"north":{"uv":[11.84,6.24,12.8,7.2],"texture":"#1"},"east":{"uv":[11.84,4.48,12.8,5.44],"texture":"#1"},"south":{"uv":[11.68,5.28,12.64,6.24],"texture":"#1"},"west":{"uv":[11.84,4.96,12.8,5.92],"texture":"#1"},"up":{"uv":[11.84,5.76,12.8,6.72],"texture":"#1"},"down":{"uv":[11.68,5.28,12.64,6.24],"texture":"#1"}}}],"display":{"thirdperson_righthand":{"translation":[-1,1.75,-2],"scale":[0.52,0.52,0.52]},"thirdperson_lefthand":{"translation":[-0.75,1.75,-2],"scale":[0.52,0.52,0.52]},"firstperson_righthand":{"translation":[1.5,4.75,-3.75],"scale":[1,1,0.78]},"firstperson_lefthand":{"rotation":[0,-14,3],"translation":[7,6,-4.5],"scale":[1,1,0.78]},"ground":{"rotation":[46,-51,0],"translation":[0,7.5,0],"scale":[0.51,0.51,0.51]},"gui":{"rotation":[28.75,66.5,0],"translation":[-0.5,4.25,0],"scale":[1.49,1.49,1.49]},"head":{"rotation":[-90,0,0],"translation":[7.25,-26.75,-1.75],"scale":[0.58,0.58,0.58]},"fixed":{"rotation":[0,90,-4],"translation":[-0.25,4.75,-1.5],"scale":[1.13,1.13,1.13]}}}